[
    {
        "word": "advantageous",
        "phonetic": "/\u02cc\u00e6dv\u0259n\u02c8te\u026ad\u0361\u0292\u0259s/",
        "phonetics": [
            {
                "text": "/\u02cc\u00e6dv\u0259n\u02c8te\u026ad\u0361\u0292\u0259s/",
                "audio": ""
            }
        ],
        "meanings": [
            {
                "partOfSpeech": "adjective",
                "definitions": [
                    {
                        "definition": "Being of advantage, beneficial.",
                        "synonyms": [
                            "behooveful",
                            "furthersome",
                            "gainful",
                            "profitable",
                            "useful"
                        ],
                        "antonyms": []
                    }
                ],
                "synonyms": [
                    "behooveful",
                    "furthersome",
                    "gainful",
                    "profitable",
                    "useful"
                ],
                "antonyms": []
            }
        ],
        "license": {
            "name": "CC BY-SA 3.0",
            "url": "https://creativecommons.org/licenses/by-sa/3.0"
        },
        "sourceUrls": [
            "https://en.wiktionary.org/wiki/advantageous"
        ]
    }
]