[
    {
        "word": "barrelhouse",
        "phonetics": [],
        "meanings": [
            {
                "partOfSpeech": "noun",
                "definitions": [
                    {
                        "definition": "A rough and tumble drinking establishment.",
                        "synonyms": [],
                        "antonyms": []
                    },
                    {
                        "definition": "A loud, percussive type of blues piano suitable for noisy bars or taverns.",
                        "synonyms": [],
                        "antonyms": []
                    }
                ],
                "synonyms": [
                    "juke",
                    "juke joint"
                ],
                "antonyms": []
            }
        ],
        "license": {
            "name": "CC BY-SA 3.0",
            "url": "https://creativecommons.org/licenses/by-sa/3.0"
        },
        "sourceUrls": [
            "https://en.wiktionary.org/wiki/barrelhouse"
        ]
    }
]